SBMLKinetics/__init__.py
SBMLKinetics/_version.py
SBMLKinetics/kinetics_classification.py
SBMLKinetics/kinetics_output.py
SBMLKinetics/types.py
SBMLKinetics/common/__init__.py
SBMLKinetics/common/constants.py
SBMLKinetics/common/exceptions.py
SBMLKinetics/common/function_definition.py
SBMLKinetics/common/helpers.py
SBMLKinetics/common/kinetic_law.py
SBMLKinetics/common/msgs.py
SBMLKinetics/common/reaction.py
SBMLKinetics/common/simple_sbml.py
SBMLKinetics/common/util.py
SBMLKinetics/data/Mammalia.zip
SBMLKinetics/data/Mus_musculus.zip
SBMLKinetics/data/Saccharomyces_cerevisiae.zip
SBMLKinetics/data/biomodels.zip
SBMLKinetics/data/cellular_organisms.zip
SBMLKinetics/data/curated.zip
SBMLKinetics/data/homo_sapiens.zip
SBMLKinetics/data/metabolic.zip
SBMLKinetics/data/non_homo.zip
SBMLKinetics/data/signalling.zip
SBMLKinetics-1.1.1.data/data/SBMLKinetics/data/Mammalia.zip
SBMLKinetics-1.1.1.data/data/SBMLKinetics/data/Mus_musculus.zip
SBMLKinetics-1.1.1.data/data/SBMLKinetics/data/Saccharomyces_cerevisiae.zip
SBMLKinetics-1.1.1.data/data/SBMLKinetics/data/biomodels.zip
SBMLKinetics-1.1.1.data/data/SBMLKinetics/data/cellular_organisms.zip
SBMLKinetics-1.1.1.data/data/SBMLKinetics/data/curated.zip
SBMLKinetics-1.1.1.data/data/SBMLKinetics/data/homo_sapiens.zip
SBMLKinetics-1.1.1.data/data/SBMLKinetics/data/metabolic.zip
SBMLKinetics-1.1.1.data/data/SBMLKinetics/data/non_homo.zip
SBMLKinetics-1.1.1.data/data/SBMLKinetics/data/signalling.zip
SBMLKinetics-1.1.1.data/scripts/constants.py
SBMLKinetics-1.1.1.data/scripts/exceptions.py
SBMLKinetics-1.1.1.data/scripts/function_definition.py
SBMLKinetics-1.1.1.data/scripts/helpers.py
SBMLKinetics-1.1.1.data/scripts/kinetic_law.py
SBMLKinetics-1.1.1.data/scripts/kinetics_classification.py
SBMLKinetics-1.1.1.data/scripts/msgs.py
SBMLKinetics-1.1.1.data/scripts/reaction.py
SBMLKinetics-1.1.1.data/scripts/simple_sbml.py
SBMLKinetics-1.1.1.data/scripts/util.py
tests/__init__.py
tests/test_function_definition.py
SBMLKinetics-1.1.1.dist-info/LICENSE
SBMLKinetics-1.1.1.dist-info/METADATA
SBMLKinetics-1.1.1.dist-info/WHEEL
SBMLKinetics-1.1.1.dist-info/top_level.txt
SBMLKinetics-1.1.1.dist-info/RECORD
