Metadata-Version: 2.1
Name: SBMLKinetics
Version: 1.1.1
Summary: Analyze SBML kinetics.
Home-page: https://github.com/SunnyXu/SBMLKinetics
Author: Jin Xu, Joseph Hellerstein
Author-email: jin.xu.phys@gmail.com
License: MIT License
Platform: UNKNOWN
Classifier: License :: OSI Approved :: MIT License
Classifier: Programming Language :: Python :: 3.8
Classifier: Programming Language :: Python :: 3.9
Classifier: Programming Language :: Python :: 3.10
Classifier: Operating System :: OS Independent
Requires-Python: >=3.8
Requires-Dist: coverage
Requires-Dist: matplotlib
Requires-Dist: nose
Requires-Dist: numpy
Requires-Dist: pandas
Requires-Dist: pylint
Requires-Dist: python-libsbml
Requires-Dist: pip (>20)
Requires-Dist: sympy
Requires-Dist: urllib3
Requires-Dist: seaborn
Requires-Dist: xlsxwriter
Requires-Dist: openpyxl
